gcloud_notebook_training/__init__.py
gcloud_notebook_training/app.py
gcloud_notebook_training/arguments_definition.py
gcloud_notebook_training/caip_job_executor.py
gcloud_notebook_training/constants.py
gcloud_notebook_training/core.py
gcloud_notebook_training/gcs_utils.py
gcloud_notebook_training/global_settings.py
gcloud_notebook_training/job_still_running_exception.py
gcloud_notebook_training/notebook_utils.py
gcloud_notebook_training/string_utils.py
gcloud_notebook_training/utils.py
gcloud_notebook_training/src/__init__.py
gcloud_notebook_training/src/arguments_definition.py
gcloud_notebook_training/src/caip_job_executor.py
gcloud_notebook_training/src/constants.py
gcloud_notebook_training/src/core.py
gcloud_notebook_training/src/gcs_utils.py
gcloud_notebook_training/src/global_settings.py
gcloud_notebook_training/src/job_still_running_exception.py
gcloud_notebook_training/src/notebook_utils.py
gcloud_notebook_training/src/string_utils.py
gcloud_notebook_training/src/utils.py
src/__init__.py
src/app.py
src/arguments_definition.py
src/caip_job_executor.py
src/constants.py
src/core.py
src/gcs_utils.py
src/job_still_running_exception.py
src/notebook_utils.py
src/string_utils.py
src/utils.py
tests/__init__.py
tests/gcs_utils_test.py
tests/notebook_utils_test.py
tests/string_utils_test.py
tests/utils_test.py
gcloud_notebook_training-0.0.23.dist-info/LICENSE
gcloud_notebook_training-0.0.23.dist-info/METADATA
gcloud_notebook_training-0.0.23.dist-info/WHEEL
gcloud_notebook_training-0.0.23.dist-info/entry_points.txt
gcloud_notebook_training-0.0.23.dist-info/top_level.txt
gcloud_notebook_training-0.0.23.dist-info/RECORD
