Metadata-Version: 2.1
Name: gcloud-notebook-training
Version: 0.0.23
Summary: Execute Jupyter notebooks in Google Cloud AI training jobs
Home-page: https://github.com/gclouduniverse/notebook_training.git
Author: Yuri Chernikov
Author-email: chernikov@google.com
License: UNKNOWN
Download-URL: https://github.com/gclouduniverse/notebook_training/archive/0.0.23.tar.gz
Platform: UNKNOWN
Classifier: Programming Language :: Python :: 3
Classifier: License :: OSI Approved :: MIT License
Classifier: Operating System :: OS Independent
Requires-Python: >=3.6
Requires-Dist: gcloud (>=0.18.3)
Requires-Dist: oauth2client (>=4.1.3)
Requires-Dist: google-api-python-client (>=1.7.11)
Requires-Dist: importlib-metadata (>=1.5.0)
Requires-Dist: google-api-core (>=1.16.0)
